{
  "comments": [
    {
      "id": "69cbd275f7f5c807c70cd3ca",
      "name": "Briva",
      "bsky": "briva.bsky.social",
      "url": "",
      "date": "2026-03-31T13:56:05.295Z",
      "text": "Finally got around to reading something on your blog! I do really like how it's laid out. As for your experiences, I'm giving sending you an astral projection of a hug. It's fucking rough out here buddy. Pretty sure I'm just gonna give up on tech soon and learn to be a barista or something. ¯\\_(ツ)_/¯"
    },
    {
      "id": "69cc4b99882bb70073c76dd2",
      "name": "ed",
      "url": "https://https://edsite.black",
      "bsky": "edsite.black",
      "date": "2026-03-31T22:32:57.209Z",
      "text": "Hey, I'm in this. I think writing out your own experience (as a very competent, detail-oriented, and social guy) in the tech field is going to be very helpful for a lot of people (and cathartic). Easy to read and easy to enjoy as always. Good work and good luck in the future. :)"
    }
  ]
}
